README.rst
setup.cfg
setup.py
comake/Comake.py
comake/ComakeException.py
comake/CompileDep.py
comake/GenComake.py
comake/GenMakefile.py
comake/GetDep.py
comake/LocalBuild.py
comake/ParseComake.py
comake/__init__.py
comake/comake.py
comake/utils.py
comake.egg-info/PKG-INFO
comake.egg-info/SOURCES.txt
comake.egg-info/dependency_links.txt
comake.egg-info/entry_points.txt
comake.egg-info/requires.txt
comake.egg-info/top_level.txt